MANIFEST.in
README
setup.py
xlsxdiff/__init__.py
xlsxdiff/changes.py
xlsxdiff/cli.py
xlsxdiff/compare.py
xlsxdiff.egg-info/PKG-INFO
xlsxdiff.egg-info/SOURCES.txt
xlsxdiff.egg-info/dependency_links.txt
xlsxdiff.egg-info/requires.txt
xlsxdiff.egg-info/top_level.txt
xlsxdiff/bin/xlsxdiff
xlsxdiff/bin/xlsxdiff.bat