Metadata-Version: 1.1
Name: xlsxdiff
Version: 0.2
Summary: compares xlsx/xlsm files
Home-page: https://bitbucket.org/adimian/xlsx-diff
Author: Eric Gazoni
Author-email: eric.gazoni@adimian.com
License: MIT/Expat
Platform: UNKNOWN
Classifier: Development Status :: 3 - Alpha
Classifier: Operating System :: MacOS :: MacOS X
Classifier: Operating System :: Microsoft :: Windows
Classifier: Operating System :: POSIX
Classifier: License :: OSI Approved :: MIT License
Classifier: Programming Language :: Python
Classifier: Programming Language :: Python :: 2.6
Classifier: Programming Language :: Python :: 2.7
Classifier: Programming Language :: Python :: 3.2
Classifier: Programming Language :: Python :: 3.3
Requires: python (>=2.6.0)
